{"R5yujSUjOGTtieWzWEj7gw==":"8-492x328.jpg","bYhNc7wrqsgJWGhvZnUw2g==":"10-492x328.jpg","e5r5KHrNZbiz1Xc8x+BWmQ==":"12-492x328.jpg","4CY/LZ7meVULWCUC9+Cgvw==":"13-492x328.jpg","eJ1Ji2OgscGM+bLBfZuQLg==":"14-492x328.jpg","agRgu44AodYrk8HJyLxgBA==":"15-492x328.jpg","5X8xymH7OPxZhcDAuoZSTA==":"16-492x328.jpg","8r92BgAbYNzJROin6Dkf8A==":"1-200x200.jpg","pB3dDwKoy1aQZ7IoMl+4Ag==":"2-200x200.jpg","jp/s0GVysOm49AJg7O7eyQ==":"3-200x200.jpg","kCVbR4imWvmRM8i/qr1uFQ==":"3-1-200x200.jpg","0AgZQrzw6QyhvuEzjKAgpw==":"3-240x240.png","cAnuy5H6LeZG34k/cS6gFQ==":"adobestock-81177232-2000x1335.jpg","UQsT2hWKeOX3gy/0fAUB/w==":"%D0%9B%D0%BE%D0%B3%D0%BE-122x102.png","DLy3yMu9iuE3eNGS5qxd3g==":"%D0%9B%D0%BE%D0%B3%D0%BE-192x160.png","hpEt4P5PZ12XSoHqLyjn9Q==":"20150815-1526-dsc06574j7-950x650.jpg","kcwr5mEwyNIZGcWrqq9BVQ==":"20150815-1526-dsc06574j7-1-950x650.jpg","mfgXVplAejkt3g6JvpG7jQ==":"91rfsvrk2cl._sl1500_-1024x683.jpg","74ClhFwL4EgG9D9zTP07Bg==":"91rfsvrk2cl._sl1500_-1-1024x683.jpg","jQJ+Cucwh0LRK0TI5Jof9w==":"atlas%20sport%2014ft%20pro-450x337.jpg","FTQihBURA9rk29whJF+Ppw==":"%D0%9B%D0%BE%D0%B3%D0%BE-559x467.png","ikmbemoQLl0qqn6JoJhz6Q==":"8-1-492x328.jpg","5IFxW/lqcWl8+DzmnThT5g==":"atlas%20sport%2016ft-393x305.jpg","Cie7yQ/JJoNCZEtsjNmidw==":"1c60a737e76b570dda42bcf011092234-800x600.jpg","wAhrdmmw682LnF2vs3CiYQ==":"jumpsport-500x313.png","C6aSsrimPnnhKF12uUDWKw==":"1c60a737e76b570dda42bcf011092234-1-800x600.jpg","R5uqHeWiaO9QSyfOAVEvow==":"6eac21b8a46621dd61c8df37403052ff-952x448.png","3AfIv9MRIdK9O+9shNgUKw==":"aee9f6ca37c616b85443d941006c8f3c-378x133.png","8IF9EzGN8mqHDkpyhDE8iQ==":"781bac8d8710bb7a1c917dd458ab9ab1-300x150.png","OeiGww7RTTteHB73jFvXkg==":"atlas%20sport%208ft%20inside-696x683.jpg","00ardVW5XmKde8F2wyWyZg==":"atlas%20sport%208ft-698x766.jpg","4SLsPWN98TUkOUENtEfTYA==":"atlas%20sport%2010ft%20iii%20pro-500x475.jpg","1j4bS+sK4URFjVvwy5TvYg==":"atlas%20sport%2010ft%20iii-250x250.jpg","Ay6IgQ1G+zfxT2smyBBsAQ==":"atlas%20sport%2010ft%20inside%20-698x688.jpg","i0YWwa/o6UZbX8lK51uFQQ==":"atlas%20sport%2010ft%20iv%20pro-490x490.jpg","9khZqIRe08ByKUKZdPWSyg==":"atlas%20sport%2010ft%20iv-669x566.jpg","ENtctraM6+cWolIQ7tUzWA==":"atlas%20sport%2012ft%20inside-649x550.jpg","LMy6o/K7ErGQ5JFpk8/gVQ==":"atlas%20sport%2012ft%20pro-450x419.jpg","4EV8pJPc4o/YvICctvLfPQ==":"atlas%20sport%2012ft-660x550.jpg","6lmxf9B4LC/ecd04OKj/Gw==":"atlas%20sport%2013ft-600x480.jpg","Aqug9bUuv3Nmg23pgQj7tg==":"atlas%20sport%2014ft%20pro-450x337.jpg","24tEwR/OYEexcqzr9ea47g==":"atlas%20sport%2014ft-411x296.jpg","OWXca6QwNDRaYo2V+lqLjw==":"atlas%20sport%2015ft%20pro-450x337.jpg","YK8gO83FkOnPLV6LjNBUPg==":"atlas%20sport%2016ft%20pro-600x512.jpg","+96VHIMz9EOAPNUSGbVz5Q==":"atlas%20sport%2016ft-393x305.jpg","42UFpOsEI3LTlI++njP3Rw==":"fitness%20trampoline%208ft-435x362.jpg","NtYE8HfzlXG6cAZfg2lajg==":"atlas%20sport%208ft-524x575.jpg","cbuf/UDpiUDqc8yap5bfjw==":"fitness%20trampoline%2010ft%20extreme-518x518.jpg","TyRjrIHhm1YC0UpzB8mBLg==":"fitness%20trampoline%2010ft%20pro-520x487.jpg","ZkpH6koI7+XBWz+WuKi9lg==":"fitness%20trampoline%2012ft-524x425.jpg","TWAcMymFu+JHZvcxhioQhQ==":"fitness%20trampoline%2012ft%20extreme-516x516.jpg","cgwVuKi5Y5lp0jt+noZf1Q==":"fitness%20trampoline%2013ft-346x350.png","H64y9G1VeMJe2ivdv0zpyg==":"fitness%20trampoline%2013ft%20extreme-350x302.jpg","Nr4WZ104ErUiIu8O2hA0Jw==":"fitness%20trampoline%2014ft-500x500.jpg","h/9Uv7nJMnwdVSbAjNRlIg==":"fitness%20trampoline%2014ft%20extreme-435x405.jpg","yMyiaedMN84iGKZzFOnBMA==":"fitness%20trampoline%2015ft%20extreme-524x348.jpg","eEZlwrQag+SzAPUPv4TcfA==":"fitness%20trampoline%2015ft-400x400.jpg","QVJwL51OWjoYv3/k4tPQWA==":"fitness%20trampoline%2016ft-225x225.jpg","OqecCIFFiGwOXNEmwBinvg==":"fitness%20trampoline%2016ft%20extreme-354x260.jpg","xDDVvRFWvatkBIyJ9TykPw==":"%D0%A1%D0%BD%D0%B8%D0%BC%D0%BE%D0%BA-475x422.png","TwKw5E5hFZ1dWApPrRMX/g==":"funfit%2010ft-524x524.jpg","5pNFh5wa9CDGsZ2HcYSOoA==":"funfit%2012ft-250x250.jpg","EXb0/Towb6JmkSV1/ZtGlg==":"funfit%2013ft-225x225.jpg","hKY0zWpo/og0Ul4kl4RDyw==":"funfit%2014ft-524x348.jpg","HYBS5nitXUu4JZzk25kxNw==":"%D0%A1%D0%BD%D0%B8%D0%BC%D0%BE%D0%BA-522x364.png","K0edMKr8G1AMmBPi67K99A==":"%D0%A1%D0%BD%D0%B8%D0%BC%D0%BE%D0%BA-524x365.png","G5/mJbgaYj/MrnruagtVvQ==":"total%20sport%208ft-340x343.jpg","rc6OMPdgVw9s0HTli5NBew==":"total%20sport%2010ft-524x393.jpg","/EJpI3J9KC+wp2uwvA49vQ==":"total%20sport%2010ft%20inside-340x316.jpg","Tj8PPF/ue1OvHVc2/34i8A==":"jump%20power%2010ft-300x300.jpg","B6H4xsX3NQZXNQ0Pv4r5Gg==":"jump%20power%2012ft-524x523.jpg","00zZUyXhpQoaC0uKo25qvA==":"product1.jpg","pa5Dkwo/T1qgW/t0h+fQvA==":"background5.jpg","yuk66gmpibf9Fxan5lRt8g==":"atlas%20sport%2012ft%20inside-524x444.jpg","JOf88xwGg7Tp1JuoxsGHjw==":"atlas%20sport%2013ft-524x419.jpg","pmsb9QtifgRgXxvj/BDctA==":"252%D1%81%D0%BC-480x524.jpg","0mRRYUV8LrJscUMd7gpWvA==":"312%D1%81%D0%BC-480x524.jpg","MAhfB/3VyBMZOQRRtfdIAQ==":"374%D1%81%D0%BC-480x524.jpg","4k5XgyOMOf555NYyJc2sYg==":"404%D1%81%D0%BC-480x524.jpg","S69ycdLjsLPuKdTZ13+lzg==":"435%D1%81%D0%BC-480x524.jpg","Exu7kB1ChMFpzkxJVfccrA==":"457%D1%81%D0%BC-480x524.jpg","DvwagLTSZAdBu/rqdFe8yQ==":"490%D1%81%D0%BC-480x524.jpg","iNsmKphP0EwoOriXx8+Dng==":"555%D1%81%D0%BC-480x524.jpg","1yXDVMzLv5OFoYwROO92Tw==":"dfc%2017ft-tr-e-374x374.jpg","rJMQZJl82mAfqdEzktRVJw==":"dfc%2017ft-tr-e-524x524.jpg","uZb91SC+hx4TLklr3gUT3A==":"dfc%2017ft-tr-e-446x446.jpg","ay+C9g3EiFQVHM3pdLCGCw==":"dfc%20kengoo%2017ft-tr-e-bas-484x484.jpg","RoY87AqsAJlwD0cZlxDPbg==":"dfc%20kengoo%2017ft-tr-e-bas-490x490.jpg","HtiJh0nBMGXMeoqlmoSfIw==":"dfc%20kengoo%2017ft-tr-e-bas-488x488.jpg","mIIbxW0r7dEZSbMPwcoYdg==":"background2.jpg","bxnba/KnzF0eFguadPHHlQ==":"logo-169x126.png","K5pSBIkh7wD1tEmF99WVug==":"trampoline-logo-267x255.jpg","DlaFYGZvbVoviOljdWIm4A==":"atlas%20sport%208ft%20inside-524x514.jpg","8Ioc898RNoPWLoUTR5ezBA==":"atlas%20sport%2012ft-524x437.jpg","etY6x8sGCb6XvQG/0i/Sng==":"dfc%20kengoo%2017ft-tr-e-bas-524x524.jpg","3HqIgLjoqVdlf492ia1z+A==":"logo_atlas_sport-289x249.png","eXWJeIoy++6zCjVsbUW4kA==":"fitness_trampoline_8ft-524x589.jpg","rtSEiNxvt5lPzCh8kkB8/w==":"atlas_sport_10ft-4-524x448.jpg","wPXjOjgOIpHypICiqDGlmQ==":"atlas_sport_12ft-524x524.jpg","VlghWCFtUWi4MGV3y/bfQQ==":"total_sport_12ft-435x367.jpg","w9X/077rJ14ph1v67eyuiA==":"%D0%A5%D0%B0%D0%BB%D0%B2%D0%B0-1024x331.png","WCpDPBV9EqM7Ak72MBthfQ==":"%D0%91%D0%B5%D0%B7%20%D0%B8%D0%BC%D0%B5%D0%BD%D0%B8-1-1200x400.jpg","vq8xmgzrJv11jr1QJ+sQiA==":"cards_master_halva_chip-436x275.png","z7xC4RYo8y00GlowB069Vw==":"rassrochka-536x195.jpg","53zP0mujjmPrY6cl6i94WQ==":"raketa2-483x341.png","f4iejhoLVQqqhp/9kW3FBA==":"raketa2-1-483x341.png","b/wKtutkKrrsVgZVPkyB5g==":"raketa2-2-483x341.png","ioJuxRGWQRGcZoxpSOGXpQ==":"1447411994-536x335.jpg","NXos5Eglg4s6jpAW8Vxdug==":"atlas%20sport%208ft-786x863.jpg","8f6uuhxYtNRGvnKckJz5gQ==":"atlas%20sport%2010ft%20inside%20-705x695.jpg","vCK6eRjkX53O7bFU9hci3A==":"funfit%2010ft-524x524.jpg","Gmk8AMVPFVhBXTKB1zAxJg==":"fitness%20trampoline%2012ft-698x566.jpg","KL8P1neXwLkHO+k/TQdWMQ==":"fitness%20trampoline%2015ft%20extreme-736x489.jpg","PPCwxEIFhBvsX/oOD5mr+g==":"02728ff2140e3760dbba6ed995254f80-611x611.jpg","uIEPQ/dJ2dsPpD18X+oZKg==":"item_images_image-1497417740-736x490.jpg","mtlPHuYCHnU6dB4HL4m1gQ==":"item_images_image-1497417741-736x490.jpg","s+dTFKoSDVRlzRBOtKDfbQ==":"jump%20power%2012ft-703x702.jpg","P15YwSmWCTlj5EvjwhqnYA==":"trampoline-logo-1-267x255.jpg","IjBHLWbNGIwNUudj+IaqVg==":"viber%20image%202019-04-16%20,%2016.58.15-736x659.jpg","66XuacImqFi9Sfj38/tjMQ==":"viber%20image%202019-04-16%20,%2016.58.15-736x624.jpg","chLJ6CmETUGm9M8OM8eJeA==":"viber%20image%202019-04-16%20,%2016.58.15-736x624.jpg","RJFRQFje6CzO6G12duc07A==":"viber%20image%202019-04-16%20,%2016.58.15-736x624.jpg","NYWMig6d1Ks7rpS9XB2rqg==":"0-02-05-6ae7e8bbf97b1625cdbf32c773c3702719277df8984ed9bed8add2fabec467e1_full-320x150.jpg","IvNAf1Ibry1y1pM3GEIN1Q==":"fitness%20trampoline%2015ft%20extreme-952x633.jpg","gf74HpZAuc7ntjyyrxCFyg==":"fitness%20trampoline%2015ft%20extreme-952x633.jpg","y8vtqysFJVPild/Rhf760A==":"item_images_image-1497417740-800x533.jpg","80LpJeviqgWMjEigGOF7mQ==":"item_images_image-1497417741-800x533.jpg"}